subgit/__init__.py
subgit/cli.py
subgit/constants.py
subgit/core.py
subgit/enums.py
subgit/exceptions.py
subgit/inspect/__init__.py
subgit/inspect/git_inspect.py
subgit-0.6.2.dist-info/LICENSE
subgit-0.6.2.dist-info/METADATA
subgit-0.6.2.dist-info/WHEEL
subgit-0.6.2.dist-info/entry_points.txt
subgit-0.6.2.dist-info/top_level.txt
subgit-0.6.2.dist-info/RECORD
