Metadata-Version: 2.1
Name: subgit
Version: 0.6.2
Summary: CLI tool 
Home-page: http://github.com/dynamist/sgit
Author: Johan Andersson
Author-email: johan@dynamist.se
Maintainer: Johan Andersson
Maintainer-email: johan@dynamist.se
License: Apache License 2.0
Classifier: Development Status :: 4 - Beta
Classifier: Intended Audience :: Developers
Classifier: Operating System :: OS Independent
Classifier: License :: OSI Approved :: Apache Software License
Classifier: Environment :: Console
Classifier: Programming Language :: Python
Classifier: Programming Language :: Python :: 3
Classifier: Programming Language :: Python :: 3.8
Classifier: Programming Language :: Python :: 3.9
Classifier: Programming Language :: Python :: 3.10
Classifier: Programming Language :: Python :: 3.11
Classifier: Natural Language :: English
Requires-Python: >=3.8
License-File: LICENSE
Requires-Dist: docopt (>=0.6.2)
Requires-Dist: ruamel.yaml (>=0.16.0)
Requires-Dist: gitpython (>=3.1.0)
Requires-Dist: packaging (>=21.3)
Provides-Extra: dev
Requires-Dist: pylint ; extra == 'dev'
Requires-Dist: ptpython ; extra == 'dev'
Provides-Extra: test
Requires-Dist: pytest ; extra == 'test'
Requires-Dist: pytest-mock ; extra == 'test'
Requires-Dist: mock ; extra == 'test'
Requires-Dist: tox ; extra == 'test'
Requires-Dist: black ; extra == 'test'
Requires-Dist: isort ; extra == 'test'
Requires-Dist: flake8 ; extra == 'test'
Provides-Extra: validation
Requires-Dist: pykwalify ; extra == 'validation'
